skydl-1.0.0rc6.dist-info/top_level.txt
skydl-1.0.0rc6.dist-info/METADATA
skydl-1.0.0rc6.dist-info/RECORD
skydl-1.0.0rc6.dist-info/WHEEL
skydl-1.0.0rc6.dist-info/LICENSE
skydl/__init__.py
skydl/job_scheduler/__init__.py
skydl/job_scheduler/task_executed_status_enum.py
skydl/job_scheduler/scheduled_task.py
skydl/job_scheduler/task_status_enum.py
skydl/job_scheduler/spark_job_scheduler.py
skydl/job_scheduler/scheduled_task_result.py
skydl/pybind11/__init__.py
skydl/pybind11/pybind11_smoke_test.py
skydl/pybind11/examples/__init__.py
skydl/pybind11/examples/demo/__init__.py
skydl/pybind11/examples/demo/cdemo.cpython-38-x86_64-linux-gnu.so
skydl/cython/__init__.py
skydl/cython/cython_smoke_test.py
skydl/cython/common/__init__.py
skydl/cython/common/common.cpython-38-x86_64-linux-gnu.so
skydl/cython/examples/__init__.py
skydl/cython/examples/demo/__init__.py
skydl/cython/examples/demo/cdemo.cpython-38-x86_64-linux-gnu.so
skydl/cython/examples/demo/setup_cython_call_cc.py
skydl/cython/examples/mcpp/__init__.py
skydl/cython/examples/mcpp/get_includes.py
skydl/cython/examples/mcpp/setup_tests.py
skydl/cython/examples/mcpp/setup.py
skydl/cython/examples/mcpp/test/container_unit_tests.cpython-38-x86_64-linux-gnu.so
skydl/common/logging_utils.py
skydl/common/__init__.py
skydl/common/common_utils.py
skydl/common/option.py
skydl/common/enhanced_ordered_dict.py
skydl/common/annotations.py
skydl/common/version.py
skydl/common/model_result.py
skydl/common/date_utils.py
skydl/common/enhanced_float.py
