Metadata-Version: 2.1
Name: skydl
Version: 1.0.0rc6
Summary: UNKNOWN
Home-page: UNKNOWN
Author: skydl-team
Author-email: UNKNOWN
License: BSD
Keywords: robot,ai,reinforcement learning,machine learning,RL,ML,tensorflow,pytorch,ray,skydl,high efficiency,deep learning
Platform: UNKNOWN
Classifier: Development Status :: 4 - Beta
Classifier: Intended Audience :: Developers
Classifier: Topic :: Scientific/Engineering :: Artificial Intelligence
Classifier: Framework :: Robot Framework :: Library
Classifier: License :: OSI Approved :: BSD License
Classifier: Programming Language :: Python :: 3.6
Classifier: Programming Language :: Python :: 3.7
Classifier: Programming Language :: Python :: 3.8
